aiologger_wrapper/__init__.py
aiologger_wrapper/config.py
aiologger_wrapper/enums.py
aiologger_wrapper-0.1.0.dist-info/licenses/LICENSE
aiologger_wrapper-0.1.0.dist-info/METADATA
aiologger_wrapper-0.1.0.dist-info/WHEEL
aiologger_wrapper-0.1.0.dist-info/top_level.txt
aiologger_wrapper-0.1.0.dist-info/RECORD
